netrun/llm/__init__.py
netrun/llm/chain.py
netrun/llm/cognition.py
netrun/llm/config.py
netrun/llm/exceptions.py
netrun/llm/py.typed
netrun/llm/adapters/__init__.py
netrun/llm/adapters/base.py
netrun/llm/adapters/claude.py
netrun/llm/adapters/ollama.py
netrun/llm/adapters/openai.py
netrun_llm/__init__.py
netrun_llm/chain.py
netrun_llm/cognition.py
netrun_llm/config.py
netrun_llm/exceptions.py
netrun_llm/adapters/__init__.py
netrun_llm/adapters/base.py
netrun_llm/adapters/claude.py
netrun_llm/adapters/ollama.py
netrun_llm/adapters/openai.py
netrun_llm-2.0.0.dist-info/METADATA
netrun_llm-2.0.0.dist-info/WHEEL
netrun_llm-2.0.0.dist-info/licenses/LICENSE
netrun_llm-2.0.0.dist-info/RECORD
