Metadata-Version: 2.4
Name: netrun-llm
Version: 2.0.0
Summary: Multi-provider LLM orchestration with fallback chains and three-tier cognition
Project-URL: Homepage, https://netrunsystems.com
Project-URL: Documentation, https://github.com/netrunsystems/netrun-service-library
Project-URL: Repository, https://github.com/netrunsystems/netrun-service-library
Project-URL: Issues, https://github.com/netrunsystems/netrun-service-library/issues
Author-email: Netrun Systems <support@netrunsystems.com>
License: MIT
License-File: LICENSE
Keywords: ai,anthropic,claude,cognition,fallback,gpt,llm,machine-learning,ollama,openai,orchestration
Classifier: Development Status :: 4 - Beta
Classifier: Intended Audience :: Developers
Classifier: License :: OSI Approved :: MIT License
Classifier: Programming Language :: Python :: 3
Classifier: Programming Language :: Python :: 3.8
Classifier: Programming Language :: Python :: 3.9
Classifier: Programming Language :: Python :: 3.10
Classifier: Programming Language :: Python :: 3.11
Classifier: Programming Language :: Python :: 3.12
Classifier: Topic :: Scientific/Engineering :: Artificial Intelligence
Classifier: Topic :: Software Development :: Libraries :: Python Modules
Classifier: Typing :: Typed
Requires-Python: >=3.8
Requires-Dist: netrun-core>=1.0.0
Requires-Dist: requests>=2.28.0
Provides-Extra: all
Requires-Dist: anthropic>=0.25.0; extra == 'all'
Requires-Dist: netrun-logging>=2.0.0; extra == 'all'
Requires-Dist: openai>=1.0.0; extra == 'all'
Provides-Extra: anthropic
Requires-Dist: anthropic>=0.25.0; extra == 'anthropic'
Provides-Extra: dev
Requires-Dist: black>=23.0.0; extra == 'dev'
Requires-Dist: mypy>=1.0.0; extra == 'dev'
Requires-Dist: netrun-logging>=2.0.0; extra == 'dev'
Requires-Dist: pytest-asyncio>=0.21.0; extra == 'dev'
Requires-Dist: pytest-cov>=4.0.0; extra == 'dev'
Requires-Dist: pytest>=7.0.0; extra == 'dev'
Requires-Dist: ruff>=0.1.0; extra == 'dev'
Provides-Extra: logging
Requires-Dist: netrun-logging>=2.0.0; extra == 'logging'
Provides-Extra: openai
Requires-Dist: openai>=1.0.0; extra == 'openai'
